context_log/__init__.py
context_log/contextlog.py
context_log-0.1.2.dist-info/LICENSE
context_log-0.1.2.dist-info/METADATA
context_log-0.1.2.dist-info/NOTICE.txt
context_log-0.1.2.dist-info/WHEEL
context_log-0.1.2.dist-info/top_level.txt
context_log-0.1.2.dist-info/RECORD
