Metadata-Version: 2.1
Name: context-log
Version: 0.1.2
Summary: A simple library to emit contextual information in structured logs (JSON)
Home-page: https://github.com/virtuability/context-log
Author: Morten Jensen
Author-email: release@virtuability.com
License: MIT
Platform: UNKNOWN
Requires-Python: >=3.6
